hiyapyco/__init__.py
hiyapyco/odyldo.py
hiyapyco/version.py
HiYaPyCo-0.7.0.dist-info/LICENSE
HiYaPyCo-0.7.0.dist-info/METADATA
HiYaPyCo-0.7.0.dist-info/WHEEL
HiYaPyCo-0.7.0.dist-info/top_level.txt
HiYaPyCo-0.7.0.dist-info/RECORD
