Metadata-Version: 2.1
Name: HiYaPyCo
Version: 0.7.0
Summary: Hierarchical Yaml Python Config
Home-page: https://github.com/zerwes/hiyapyco
Author: Klaus Zerwes zero-sys.net
Author-email: zerwes@users.noreply.github.com
License: GPLv3
Keywords: configuration parser yaml
Platform: any
Classifier: Development Status :: 5 - Production/Stable
Classifier: Intended Audience :: Developers
Classifier: Intended Audience :: System Administrators
Classifier: License :: OSI Approved :: GNU General Public License v3 or later (GPLv3+)
Classifier: Programming Language :: Python :: 3
Classifier: Programming Language :: Python :: 3 :: Only
Classifier: Programming Language :: Python :: 3.9
Classifier: Programming Language :: Python :: 3.11
License-File: LICENSE
Requires-Dist: Jinja2 (<4,>3)
Requires-Dist: MarkupSafe (<4)
Requires-Dist: PyYAML (<7)
